ppao/__init__.py
ppao/constants.py
ppao/custom_types.py
ppao/exceptions.py
ppao/grouper.py
ppao/matrix.py
ppao/settings.py
ppao/solver.py
ppao-1.0.dist-info/LICENSE
ppao-1.0.dist-info/METADATA
ppao-1.0.dist-info/WHEEL
ppao-1.0.dist-info/RECORD
