Metadata-Version: 2.1
Name: ppao
Version: 1.0
Summary: Reduce repeated data handler calls by the operations grouping.
Author: Alex Borontov
Author-email: anborontov@gmail.com
Requires-Python: >=3.10,<4.0
Classifier: Programming Language :: Python :: 3
Classifier: Programming Language :: Python :: 3.10
Classifier: Programming Language :: Python :: 3.11
Requires-Dist: numpy (==1.24.3)
